{
    "latestdata": {
        "data": [
            {
                "DTF": "1825.6 nm",
                "DTL": "0.0 nm",
                "Boat": "MACIF Santé Prévoyance",
                "Rank": "1",
                "Country": "FR",
                "Time_FR": "18:30 FR",
                "VMG_24h": "14.4 kts",
                "Latitude": "25°53.52'N",
                "Longitude": "30°01.69'W",
                "Speed_24h": "15.3 kts",
                "VMG_30min": "14.8 kts",
                "CountryFlag": "https://purecatamphetamine.github.io/country-flag-icons/3x2/FR.svg",
                "Heading_24h": "15°",
                "Speed_30min": "16.3 kts",
                "Distance_24h": "366.2 nm",
                "Skipper_Boat": "Charlie Dalin",
                "Heading_30min": "14°",
                "Distance_30min": "8.2 nm",
                "VMG_LastReport": "12.9 kts",
                "Speed_LastReport": "14.2 kts",
                "Heading_LastReport": "13°",
                "Distance_LastReport": "56.9 nm"
            },
            {
                "DTF": "8746.5 nm",
                "DTL": "6920.9 nm",
                "Boat": "Singchain Team Haikou",
                "Rank": "32",
                "Country": "CN",
                "Time_FR": "18:30 FR",
                "VMG_24h": "11.0 kts",
                "Latitude": "54°21.22'S",
                "Longitude": "119°01.32'W",
                "Speed_24h": "12.5 kts",
                "VMG_30min": "10.6 kts",
                "CountryFlag": "https://purecatamphetamine.github.io/country-flag-icons/3x2/CN.svg",
                "Heading_24h": "89°",
                "Speed_30min": "12.4 kts",
                "Distance_24h": "300.4 nm",
                "Skipper_Boat": "Jingkun Xu",
                "Heading_30min": "83°",
                "Distance_30min": "6.2 nm",
                "VMG_LastReport": "11.0 kts",
                "Speed_LastReport": "13.3 kts",
                "Heading_LastReport": "81°",
                "Distance_LastReport": "53.2 nm"
            },
            {
                "DTF": "9842.2 nm",
                "DTL": "8016.6 nm",
                "Boat": "Coup de Pouce",
                "Rank": "33",
                "Country": "FR",
                "Time_FR": "18:30 FR",
                "VMG_24h": "9.0 kts",
                "Latitude": "55°30.46'S",
                "Longitude": "150°44.56'W",
                "Speed_24h": "9.0 kts",
                "VMG_30min": "9.8 kts",
                "CountryFlag": "https://purecatamphetamine.github.io/country-flag-icons/3x2/FR.svg",
                "Heading_24h": "90°",
                "Speed_30min": "10.0 kts",
                "Distance_24h": "215.6 nm",
                "Skipper_Boat": "Manuel Cousin",
                "Heading_30min": "95°",
                "Distance_30min": "4.9 nm",
                "VMG_LastReport": "9.7 kts",
                "Speed_LastReport": "9.9 kts",
                "Heading_LastReport": "98°",
                "Distance_LastReport": "39.6 nm"
            }
        ],
        "lastUpdate": "19h00"
    }
}